mysql_mcp_server/__init__.py
mysql_mcp_server/server.py
mysql_mcp_server_financeblue-0.2.3.dist-info/licenses/LICENSE
mysql_mcp_server_financeblue-0.2.3.dist-info/METADATA
mysql_mcp_server_financeblue-0.2.3.dist-info/WHEEL
mysql_mcp_server_financeblue-0.2.3.dist-info/entry_points.txt
mysql_mcp_server_financeblue-0.2.3.dist-info/top_level.txt
mysql_mcp_server_financeblue-0.2.3.dist-info/RECORD
