Metadata-Version: 2.4
Name: mysql_mcp_server_financeblue
Version: 0.2.3
Summary: A Model Context Protocol (MCP) server that enables secure interaction with MySQL databases. This server allows AI assistants to list tables, read data, and execute SQL queries through a controlled interface, making database exploration and analysis safer and more structured.
Author-email: FinanceBlue <FinanceBlue@test.com>
Requires-Python: >=3.11
License-File: LICENSE
Requires-Dist: build>=1.2.2.post1
Requires-Dist: mcp>=1.0.0
Requires-Dist: mysql-connector-python>=9.1.0
Requires-Dist: twine>=6.1.0
Dynamic: license-file
